{
  "users": [
    {
      "id": "1",
      "name": "Nicolás",
      "email": "nico@example.com",
      "password": "12345678"
    },
    {
      "id": "2",
      "name": "Ana",
      "email": "ana@example.com",
      "password": "12345678"
    }
  ],
  "recipes": [
    {
      "id": "1",
      "userId": "1",
      "title": "Tortilla de patatas",
      "description": "Una receta clásica española.",
      "ingredients": [
        "4 patatas",
        "6 huevos",
        "1 cebolla",
        "sal"
      ],
      "instructions": [
        "Pelar y cortar las patatas en rodajas.",
        "Freír las patatas en aceite caliente hasta que estén doradas.",
        "Batir los huevos y añadir las patatas fritas.",
        "Verter la mezcla en una sartén caliente y cocinar a fuego lento.",
        "Dar la vuelta a la tortilla y cocinar por el otro lado.",
        "Servir caliente o fría."
      ],
      "image": "https://upload.wikimedia.org/wikipedia/commons/thumb/b/b7/Totilla_Espa%C3%B1ola_-_Tapa_plato.JPG/1200px-Totilla_Espa%C3%B1ola_-_Tapa_plato.JPG?20130515212345"
    },
    {
      "id": "2",
      "userId": "1",
      "title": "Ensalada César",
      "description": "Fresca y sencilla.",
      "ingredients": [
        "Lechuga romana",
        "Pechuga de pollo",
        "Queso parmesano",
        "Picatostes",
        "Salsa César"
      ],
      "instructions": [
        "Cortar la lechuga y colocar en un bol.",
        "Añadir el pollo a la plancha en tiras.",
        "Espolvorear queso y picatostes.",
        "Aliñar con salsa César al gusto."
      ],
      "image": "https://c.pxhere.com/photos/db/f5/appetizer_bowl_ceramic_chicken_cooking_crispy_cuisine_delicious-1529253.jpg!d"
    }
  ]
}
